poltergust_luigi_utils
