Metadata-Version: 2.1
Name: poltergust-luigi-utils
Version: 0.0.9
Summary: Luigi utils
Home-page: https://github.com/emerald-geomodelling/poltergust-luigi-utils
Author: Egil Moeller
Author-email: em@emrld.no
License-File: LICENSE
